main.py
exa_cli-0.1.0.dist-info/licenses/LICENSE
exa_cli-0.1.0.dist-info/METADATA
exa_cli-0.1.0.dist-info/WHEEL
exa_cli-0.1.0.dist-info/entry_points.txt
exa_cli-0.1.0.dist-info/top_level.txt
exa_cli-0.1.0.dist-info/RECORD
