Metadata-Version: 2.4
Name: exa-cli
Version: 0.1.0
Summary: Command-line interface for Exa neural search API
Author: Fergus Fettes
License: MIT
Project-URL: Homepage, https://github.com/ffettes/exa-cli
Project-URL: Repository, https://github.com/ffettes/exa-cli
Keywords: exa,search,cli,neural-search,ai
Classifier: Development Status :: 3 - Alpha
Classifier: Environment :: Console
Classifier: Intended Audience :: Developers
Classifier: License :: OSI Approved :: MIT License
Classifier: Programming Language :: Python :: 3
Classifier: Programming Language :: Python :: 3.13
Classifier: Topic :: Utilities
Requires-Python: >=3.13
License-File: LICENSE
Requires-Dist: exa-py>=1.16.1
Requires-Dist: rich>=14.2.0
Requires-Dist: typer>=0.19.2
Dynamic: license-file
